buster/__init__.py
buster/client.py
buster/validation.py
buster/resources/__init__.py
buster/resources/airflow/__init__.py
buster/resources/airflow/base.py
buster/resources/airflow/get_logs.py
buster/resources/airflow/models.py
buster/resources/airflow/types.py
buster/resources/airflow/utils.py
buster/resources/airflow/v2_11.py
buster/resources/airflow/v3.py
buster/types/__init__.py
buster/types/api.py
buster/types/debug.py
buster/utils/__init__.py
buster/utils/http.py
buster/utils/logger.py
buster/utils/url.py
buster_sdk-0.2.1.dist-info/METADATA
buster_sdk-0.2.1.dist-info/WHEEL
buster_sdk-0.2.1.dist-info/licenses/LICENSE
buster_sdk-0.2.1.dist-info/RECORD
