Metadata-Version: 2.4
Name: buster-sdk
Version: 0.2.1
Summary: A Python SDK for Buster
Project-URL: Homepage, https://github.com/buster-so/python-sdk
Project-URL: Bug Tracker, https://github.com/buster-so/python-sdk/issues
Author-email: Buster <support@buster.so>
License-File: LICENSE
Classifier: License :: OSI Approved :: MIT License
Classifier: Operating System :: OS Independent
Classifier: Programming Language :: Python :: 3
Requires-Python: >=3.9
Requires-Dist: pydantic>=2.0.0
Requires-Dist: requests
Requires-Dist: typing-extensions>=4.0.0
Provides-Extra: dev
Requires-Dist: build; extra == 'dev'
Requires-Dist: mypy; extra == 'dev'
Requires-Dist: pytest; extra == 'dev'
Requires-Dist: python-semantic-release; extra == 'dev'
Requires-Dist: ruff; extra == 'dev'
Requires-Dist: twine; extra == 'dev'
Requires-Dist: types-requests; extra == 'dev'
